MANIFEST.in
README.md
requirements.txt
setup.py
src/BrowserMobProxyLibrary/__init__.py
src/BrowserMobProxyLibrary/version.py
src/robotframework_browsermobproxylibrary.egg-info/PKG-INFO
src/robotframework_browsermobproxylibrary.egg-info/SOURCES.txt
src/robotframework_browsermobproxylibrary.egg-info/dependency_links.txt
src/robotframework_browsermobproxylibrary.egg-info/requires.txt
src/robotframework_browsermobproxylibrary.egg-info/top_level.txt