Metadata-Version: 2.1
Name: robotframework-browsermobproxylibrary
Version: 0.1.3
Summary: BrowserMob Proxy library for Robot Framework
Home-page: https://github.com/s4int/robotframework-BrowserMobProxyLibrary
Author: Marcin Mierzejewski
Author-email: <mmierz@gmail.com>
License: Apache License 2.0
Keywords: robotframework testing selenium selenium2 webdriver web browsermob proxy
Platform: any
Classifier: Development Status :: 5 - Production/Stable
Classifier: License :: OSI Approved :: Apache Software License
Classifier: Operating System :: OS Independent
Classifier: Programming Language :: Python
Classifier: Topic :: Software Development :: Testing
Classifier: Programming Language :: Python :: 2
Classifier: Programming Language :: Python :: 2.7
Classifier: Programming Language :: Python :: 3
Classifier: Programming Language :: Python :: 3.6
